mux.v
 module mux(f,a,s,clk);
		input [7:0]a;
		input [2:0]s;
		input clk;
		output reg f;
	integer k,i;
always @(posedge clk)
	
	for(k=0;k<=7;k=k+1)
	  	begin
			for(i=0;i<=2;i=i+1)
				begin
			      if(s==i)
			       f<=a+k;
				end
				
        end
endmodule

mux_tb.v
`include "mux.v"
module mux_tb;
	reg [7:0]a;
	reg [2:0]s;
	wire f;
	reg clk;
	
mux g(
	.f(f),
	.a(a),
	.s(s),
	.clk(clk)
	);

initial begin
	$dumpfile("mux.vcd");
	$dumpvars(0, mux_tb);
	clk=0; s=0; a=0;
#100 $finish;
end

always #5 clk=~clk;
always #10 a=a+1;
always #15 s=s+1;

endmodule

mux.vcd
$date
	Wed Apr 12 19:36:44 2023
$end
$version
	Icarus Verilog
$end
$timescale
	1s
$end
$scope module mux_tb $end
$var wire 1 ! f $end
$var reg 8 " a [7:0] $end
$var reg 1 # clk $end
$var reg 3 $ s [2:0] $end
$scope module g $end
$var wire 8 % a [7:0] $end
$var wire 1 & clk $end
$var wire 3 ' s [2:0] $end
$var reg 1 ( f $end
$var integer 32 ) i [31:0] $end
$var integer 32 * k [31:0] $end
$upscope $end
$upscope $end
$enddefinitions $end
#0
$dumpvars
bx *
bx )
x(
b0 '
0&
b0 %
b0 $
0#
b0 "
x!
$end
#5
1(
1!
b11 )
b1000 *
1#
1&
#10
0#
0&
b1 "
b1 %
#15
0(
0!
b11 )
b1000 *
1#
1&
b1 $
b1 '
#20
0#
0&
b10 "
b10 %
#25
1(
1!
b11 )
b1000 *
1#
1&
#30
0#
0&
b11 "
b11 %
b10 $
b10 '
#35
0(
0!
b11 )
b1000 *
1#
1&
#40
0#
0&
b100 "
b100 %
#45
b11 )
b1000 *
1#
1&
b11 $
b11 '
#50
0#
0&
b101 "
b101 %
#55
b11 )
b1000 *
1#
1&
#60
0#
0&
b110 "
b110 %
b100 $
b100 '
#65
b11 )
b1000 *
1#
1&
#70
0#
0&
b111 "
b111 %
#75
b11 )
b1000 *
1#
1&
b101 $
b101 '
#80
0#
0&
b1000 "
b1000 %
#85
b11 )
b1000 *
1#
1&
#90
0#
0&
b1001 "
b1001 %
b110 $
b110 '
#95
b11 )
b1000 *
1#
1&
#100
0#
0&
b1010 "
b1010 %
#105
b11 )
b1000 *
1#
1&
b111 $
b111 '
#110
0#
0&
b1011 "
b1011 %
#115
b11 )
b1000 *
1#
1&
#120
0#
0&
b1100 "
b1100 %
b0 $
b0 '
#125
1(
1!
b11 )
b1000 *
1#
1&
#130
0#
0&
b1101 "
b1101 %
#135
0(
0!
b11 )
b1000 *
1#
1&
b1 $
b1 '
#140
0#
0&
b1110 "
b1110 %
#145
1(
1!
b11 )
b1000 *
1#
1&
#150
0#
0&
b1111 "
b1111 %
b10 $
b10 '
#155
0(
0!
b11 )
b1000 *
1#
1&
#160
0#
0&
b10000 "
b10000 %
#165
b11 )
b1000 *
1#
1&
b11 $
b11 '
#170
0#
0&
b10001 "
b10001 %
#175
b11 )
b1000 *
1#
1&
#180
0#
0&
b10010 "
b10010 %
b100 $
b100 '
#185
b11 )
b1000 *
1#
1&
#190
0#
0&
b10011 "
b10011 %
#195
b11 )
b1000 *
1#
1&
b101 $
b101 '
#200
0#
0&
b10100 "
b10100 %
#205
b11 )
b1000 *
1#
1&
#210
0#
0&
b10101 "
b10101 %
b110 $
b110 '
#215
b11 )
b1000 *
1#
1&
#220
0#
0&
b10110 "
b10110 %
#225
b11 )
b1000 *
1#
1&
b111 $
b111 '
#230
0#
0&
b10111 "
b10111 %
#235
b11 )
b1000 *
1#
1&
#240
0#
0&
b11000 "
b11000 %
b0 $
b0 '
#245
1(
1!
b11 )
b1000 *
1#
1&
#250
0#
0&
b11001 "
b11001 %
#255
0(
0!
b11 )
b1000 *
1#
1&
b1 $
b1 '
#260
0#
0&
b11010 "
b11010 %
#265
1(
1!
b11 )
b1000 *
1#
1&
#270
0#
0&
b11011 "
b11011 %
b10 $
b10 '
#275
0(
0!
b11 )
b1000 *
1#
1&
#280
0#
0&
b11100 "
b11100 %
#285
b11 )
b1000 *
1#
1&
b11 $
b11 '
#290
0#
0&
b11101 "
b11101 %
#295
b11 )
b1000 *
1#
1&
#300
0#
0&
b11110 "
b11110 %
b100 $
b100 '
#305
b11 )
b1000 *
1#
1&
#310
0#
0&
b11111 "
b11111 %
#315
b11 )
b1000 *
1#
1&
b101 $
b101 '
#320
0#
0&
b100000 "
b100000 %
#325
b11 )
b1000 *
1#
1&
#330
0#
0&
b100001 "
b100001 %
b110 $
b110 '
#335
b11 )
b1000 *
1#
1&
#340
0#
0&
b100010 "
b100010 %
#345
b11 )
b1000 *
1#
1&
b111 $
b111 '
#350
0#
0&
b100011 "
b100011 %
#355
b11 )
b1000 *
1#
1&
#360
0#
0&
b100100 "
b100100 %
b0 $
b0 '
#365
1(
1!
b11 )
b1000 *
1#
1&
#370
0#
0&
b100101 "
b100101 %
#375
0(
0!
b11 )
b1000 *
1#
1&
b1 $
b1 '
#380
0#
0&
b100110 "
b100110 %
#385
1(
1!
b11 )
b1000 *
1#
1&
#390
0#
0&
b100111 "
b100111 %
b10 $
b10 '
#395
0(
0!
b11 )
b1000 *
1#
1&
#400
0#
0&
b101000 "
b101000 %
#405
b11 )
b1000 *
1#
1&
b11 $
b11 '
#410
0#
0&
b101001 "
b101001 %
#415
b11 )
b1000 *
1#
1&
#420
0#
0&
b101010 "
b101010 %
b100 $
b100 '
#425
b11 )
b1000 *
1#
1&
#430
0#
0&
b101011 "
b101011 %
#435
b11 )
b1000 *
1#
1&
b101 $
b101 '
#440
0#
0&
b101100 "
b101100 %
#445
b11 )
b1000 *
1#
1&
#450
0#
0&
b101101 "
b101101 %
b110 $
b110 '
#455
b11 )
b1000 *
1#
1&
#460
0#
0&
b101110 "
b101110 %
#465
b11 )
b1000 *
1#
1&
b111 $
b111 '
#470
0#
0&
b101111 "
b101111 %
#475
b11 )
b1000 *
1#
1&
#480
0#
0&
b110000 "
b110000 %
b0 $
b0 '
#485
1(
1!
b11 )
b1000 *
1#
1&
#490
0#
0&
b110001 "
b110001 %
#495
0(
0!
b11 )
b1000 *
1#
1&
b1 $
b1 '
#500
0#
0&
b110010 "
b110010 %
#505
1(
1!
b11 )
b1000 *
1#
1&
#510
0#
0&
b110011 "
b110011 %
b10 $
b10 '
#515
0(
0!
b11 )
b1000 *
1#
1&
#520
0#
0&
b110100 "
b110100 %
#525
b11 )
b1000 *
1#
1&
b11 $
b11 '
#530
0#
0&
b110101 "
b110101 %
#535
b11 )
b1000 *
1#
1&
#540
0#
0&
b110110 "
b110110 %
b100 $
b100 '
#545
b11 )
b1000 *
1#
1&
#550
0#
0&
b110111 "
b110111 %
#555
b11 )
b1000 *
1#
1&
b101 $
b101 '
#560
0#
0&
b111000 "
b111000 %
#565
b11 )
b1000 *
1#
1&
#570
0#
0&
b111001 "
b111001 %
b110 $
b110 '
#575
b11 )
b1000 *
1#
1&
#580
0#
0&
b111010 "
b111010 %
#585
b11 )
b1000 *
1#
1&
b111 $
b111 '
#590
0#
0&
b111011 "
b111011 %
#595
b11 )
b1000 *
1#
1&
#600
0#
0&
b111100 "
b111100 %
b0 $
b0 '
#605
1(
1!
b11 )
b1000 *
1#
1&
#610
0#
0&
b111101 "
b111101 %
#615
0(
0!
b11 )
b1000 *
1#
1&
b1 $
b1 '
#620
0#
0&
b111110 "
b111110 %
#625
1(
1!
b11 )
b1000 *
1#
1&
#630
0#
0&
b111111 "
b111111 %
b10 $
b10 '
#635
0(
0!
b11 )
b1000 *
1#
1&
#640
0#
0&
b1000000 "
b1000000 %
#645
b11 )
b1000 *
1#
1&
b11 $
b11 '
#650
0#
0&
b1000001 "
b1000001 %
#655
b11 )
b1000 *
1#
1&
#660
0#
0&
b1000010 "
b1000010 %
b100 $
b100 '
#665
b11 )
b1000 *
1#
1&
#670
0#
0&
b1000011 "
b1000011 %
#675
b11 )
b1000 *
1#
1&
b101 $
b101 '
#680
0#
0&
b1000100 "
b1000100 %
#685
b11 )
b1000 *
1#
1&
#690
0#
0&
b1000101 "
b1000101 %
b110 $
b110 '
#695
b11 )
b1000 *
1#
1&
#700
0#
0&
b1000110 "
b1000110 %
#705
b11 )
b1000 *
1#
1&
b111 $
b111 '
#710
0#
0&
b1000111 "
b1000111 %
#715
b11 )
b1000 *
1#
1&
#720
0#
0&
b1001000 "
b1001000 %
b0 $
b0 '
#725
1(
1!
b11 )
b1000 *
1#
1&
#730
0#
0&
b1001001 "
b1001001 %
#735
0(
0!
b11 )
b1000 *
1#
1&
b1 $
b1 '
#740
0#
0&
b1001010 "
b1001010 %
#745
1(
1!
b11 )
b1000 *
1#
1&
#750
0#
0&
b1001011 "
b1001011 %
b10 $
b10 '
#755
0(
0!
b11 )
b1000 *
1#
1&
#760
0#
0&
b1001100 "
b1001100 %
#765
b11 )
b1000 *
1#
1&
b11 $
b11 '
#770
0#
0&
b1001101 "
b1001101 %
#775
b11 )
b1000 *
1#
1&
#780
0#
0&
b1001110 "
b1001110 %
b100 $
b100 '
#785
b11 )
b1000 *
1#
1&
#790
0#
0&
b1001111 "
b1001111 %
#795
b11 )
b1000 *
1#
1&
b101 $
b101 '
#800
0#
0&
b1010000 "
b1010000 %
#805
b11 )
b1000 *
1#
1&
#810
0#
0&
b1010001 "
b1010001 %
b110 $
b110 '
#815
b11 )
b1000 *
1#
1&
#820
0#
0&
b1010010 "
b1010010 %
#825
b11 )
b1000 *
1#
1&
b111 $
b111 '
#830
0#
0&
b1010011 "
b1010011 %
#835
b11 )
b1000 *
1#
1&
#840
0#
0&
b1010100 "
b1010100 %
b0 $
b0 '
#845
1(
1!
b11 )
b1000 *
1#
1&
#850
0#
0&
b1010101 "
b1010101 %
#855
0(
0!
b11 )
b1000 *
1#
1&
b1 $
b1 '
#860
0#
0&
b1010110 "
b1010110 %
#865
1(
1!
b11 )
b1000 *
1#
1&
#870
0#
0&
b1010111 "
b1010111 %
b10 $
b10 '
#875
0(
0!
b11 )
b1000 *
1#
1&
#880
0#
0&
b1011000 "
b1011000 %
#885
b11 )
b1000 *
1#
1&
b11 $
b11 '
#890
0#
0&
b1011001 "
b1011001 %
#895
b11 )
b1000 *
1#
1&
#900
0#
0&
b1011010 "
b1011010 %
b100 $
b100 '
#905
b11 )
b1000 *
1#
1&
#910
0#
0&
b1011011 "
b1011011 %
#915
b11 )
b1000 *
1#
1&
b101 $
b101 '
#920
0#
0&
b1011100 "
b1011100 %
#925
b11 )
b1000 *
1#
1&
#930
0#
0&
b1011101 "
b1011101 %
b110 $
b110 '
#935
b11 )
b1000 *
1#
1&
#940
0#
0&
b1011110 "
b1011110 %
#945
b11 )
b1000 *
1#
1&
b111 $
b111 '
#950
0#
0&
b1011111 "
b1011111 %
#955
b11 )
b1000 *
1#
1&
#960
0#
0&
b1100000 "
b1100000 %
b0 $
b0 '
#965
1(
1!
b11 )
b1000 *
1#
1&
#970
0#
0&
b1100001 "
b1100001 %
#975
0(
0!
b11 )
b1000 *
1#
1&
b1 $
b1 '
#980
0#
0&
b1100010 "
b1100010 %
#985
1(
1!
b11 )
b1000 *
1#
1&
#990
0#
0&
b1100011 "
b1100011 %
b10 $
b10 '
#995
0(
0!
b11 )
b1000 *
1#
1&
#1000
0#
0&
b1100100 "
b1100100 %
#1005
b11 )
b1000 *
1#
1&
b11 $
b11 '
#1010
0#
0&
b1100101 "
b1100101 %
#1015
b11 )
b1000 *
1#
1&
#1020
0#
0&
b1100110 "
b1100110 %
b100 $
b100 '
#1025
b11 )
b1000 *
1#
1&
#1030
0#
0&
b1100111 "
b1100111 %
#1035
b11 )
b1000 *
1#
1&
b101 $
b101 '
#1040
0#
0&
b1101000 "
b1101000 %
#1045
b11 )
b1000 *
1#
1&
#1050
0#
0&
b1101001 "
b1101001 %
b110 $
b110 '
#1055
b11 )
b1000 *
1#
1&
#1060
0#
0&
b1101010 "
b1101010 %
#1065
b11 )
b1000 *
1#
1&
b111 $
b111 '
#1070
0#
0&
b1101011 "
b1101011 %
#1075
b11 )
b1000 *
1#
1&
#1080
0#
0&
b1101100 "
b1101100 %
b0 $
b0 '
#1085
1(
1!
b11 )
b1000 *
1#
1&
#1090
0#
0&
b1101101 "
b1101101 %
#1095
0(
0!
b11 )
b1000 *
1#
1&
b1 $
b1 '
#1100
0#
0&
b1101110 "
b1101110 %
#1105
1(
1!
b11 )
b1000 *
1#
1&
#1110
0#
0&
b1101111 "
b1101111 %
b10 $
b10 '
#1115
0(
0!
b11 )
b1000 *
1#
1&
#1120
0#
0&
b1110000 "
b1110000 %
#1125
b11 )
b1000 *
1#
1&
b11 $
b11 '
#1130
0#
0&
b1110001 "
b1110001 %
#1135
b11 )
b1000 *
1#
1&
#1140
0#
0&
b1110010 "
b1110010 %
b100 $
b100 '
#1145
b11 )
b1000 *
1#
1&
#1150
0#
0&
b1110011 "
b1110011 %
#1155
b11 )
b1000 *
1#
1&
b101 $
b101 '
#1160
0#
0&
b1110100 "
b1110100 %
#1165
b11 )
b1000 *
1#
1&
#1170
0#
0&
b1110101 "
b1110101 %
b110 $
b110 '
#1175
b11 )
b1000 *
1#
1&
#1180
0#
0&
b1110110 "
b1110110 %
#1185
b11 )
b1000 *
1#
1&
b111 $
b111 '
#1190
0#
0&
b1110111 "
b1110111 %
#1195
b11 )
b1000 *
1#
1&
#1200
0#
0&
b1111000 "
b1111000 %
b0 $
b0 '
#1205
1(
1!
b11 )
b1000 *
1#
1&
#1210
0#
0&
b1111001 "
b1111001 %
#1215
0(
0!
b11 )
b1000 *
1#
1&
b1 $
b1 '
#1220
0#
0&
b1111010 "
b1111010 %
#1225
1(
1!
b11 )
b1000 *
1#
1&
#1230
0#
0&
b1111011 "
b1111011 %
b10 $
b10 '
#1235
0(
0!
b11 )
b1000 *
1#
1&
#1240
0#
0&
b1111100 "
b1111100 %
#1245
b11 )
b1000 *
1#
1&
b11 $
b11 '
#1250
0#
0&
b1111101 "
b1111101 %
#1255
b11 )
b1000 *
1#
1&
#1260
0#
0&
b1111110 "
b1111110 %
b100 $
b100 '
#1265
b11 )
b1000 *
1#
1&
#1270
0#
0&
b1111111 "
b1111111 %
#1275
b11 )
b1000 *
1#
1&
b101 $
b101 '
#1280
0#
0&
b10000000 "
b10000000 %
#1285
b11 )
b1000 *
1#
1&
#1290
0#
0&
b10000001 "
b10000001 %
b110 $
b110 '
#1295
b11 )
b1000 *
1#
1&
#1300
0#
0&
b10000010 "
b10000010 %
#1305
b11 )
b1000 *
1#
1&
b111 $
b111 '
#1310
0#
0&
b10000011 "
b10000011 %
#1315
b11 )
b1000 *
1#
1&
#1320
0#
0&
b10000100 "
b10000100 %
b0 $
b0 '
#1325
1(
1!
b11 )
b1000 *
1#
1&
#1330
0#
0&
b10000101 "
b10000101 %
#1335
0(
0!
b11 )
b1000 *
1#
1&
b1 $
b1 '
#1340
0#
0&
b10000110 "
b10000110 %
#1345
1(
1!
b11 )
b1000 *
1#
1&
#1350
0#
0&
b10000111 "
b10000111 %
b10 $
b10 '
#1355
0(
0!
b11 )
b1000 *
1#
1&
#1360
0#
0&
b10001000 "
b10001000 %
#1365
b11 )
b1000 *
1#
1&
b11 $
b11 '
#1370
0#
0&
b10001001 "
b10001001 %
#1375
b11 )
b1000 *
1#
1&
#1380
0#
0&
b10001010 "
b10001010 %
b100 $
b100 '
#1385
b11 )
b1000 *
1#
1&
#1390
0#
0&
b10001011 "
b10001011 %
#1395
b11 )
b1000 *
1#
1&
b101 $
b101 '
#1400
0#
0&
b10001100 "
b10001100 %
#1405
b11 )
b1000 *
1#
1&
#1410
0#
0&
b10001101 "
b10001101 %
b110 $
b110 '
#1415
b11 )
b1000 *
1#
1&
#1420
0#
0&
b10001110 "
b10001110 %
#1425
b11 )
b1000 *
1#
1&
b111 $
b111 '
#1430
0#
0&
b10001111 "
b10001111 %
#1435
b11 )
b1000 *
1#
1&
#1440
0#
0&
b10010000 "
b10010000 %
b0 $
b0 '
#1445
1(
1!
b11 )
b1000 *
1#
1&
#1450
0#
0&
b10010001 "
b10010001 %
#1455
0(
0!
b11 )
b1000 *
1#
1&
b1 $
b1 '
#1460
0#
0&
b10010010 "
b10010010 %
#1465
1(
1!
b11 )
b1000 *
1#
1&
#1470
0#
0&
b10010011 "
b10010011 %
b10 $
b10 '
#1475
0(
0!
b11 )
b1000 *
1#
1&
#1480
0#
0&
b10010100 "
b10010100 %
#1485
b11 )
b1000 *
1#
1&
b11 $
b11 '
#1490
0#
0&
b10010101 "
b10010101 %
#1495
b11 )
b1000 *
1#
1&
#1500
0#
0&
b10010110 "
b10010110 %
b100 $
b100 '
#1505
b11 )
b1000 *
1#
1&
#1510
0#
0&
b10010111 "
b10010111 %
#1515
b11 )
b1000 *
1#
1&
b101 $
b101 '
#1520
0#
0&
b10011000 "
b10011000 %
#1525
b11 )
b1000 *
1#
1&
#1530
0#
0&
b10011001 "
b10011001 %
b110 $
b110 '
#1535
b11 )
b1000 *
1#
1&
#1540
0#
0&
b10011010 "
b10011010 %
#1545
b11 )
b1000 *
1#
1&
b111 $
b111 '
#1550
0#
0&
b10011011 "
b10011011 %
#1555
b11 )
b1000 *
1#
1&
#1560
0#
0&
b10011100 "
b10011100 %
b0 $
b0 '
#1565
1(
1!
b11 )
b1000 *
1#
1&
#1570
0#
0&
b10011101 "
b10011101 %
#1575
0(
0!
b11 )
b1000 *
1#
1&
b1 $
b1 '
#1580
0#
0&
b10011110 "
b10011110 %
#1585
1(
1!
b11 )
b1000 *
1#
1&
#1590
0#
0&
b10011111 "
b10011111 %
b10 $
b10 '
#1595
0(
0!
b11 )
b1000 *
1#
1&
#1600
0#
0&
b10100000 "
b10100000 %
#1605
b11 )
b1000 *
1#
1&
b11 $
b11 '
#1610
0#
0&
b10100001 "
b10100001 %
#1615
b11 )
b1000 *
1#
1&
#1620
0#
0&
b10100010 "
b10100010 %
b100 $
b100 '
#1625
b11 )
b1000 *
1#
1&
#1630
0#
0&
b10100011 "
b10100011 %
#1635
b11 )
b1000 *
1#
1&
b101 $
b101 '
#1640
0#
0&
b10100100 "
b10100100 %
#1645
b11 )
b1000 *
1#
1&
#1650
0#
0&
b10100101 "
b10100101 %
b110 $
b110 '
#1655
b11 )
b1000 *
1#
1&
#1660
0#
0&
b10100110 "
b10100110 %
#1665
b11 )
b1000 *
1#
1&
b111 $
b111 '
#1670
0#
0&
b10100111 "
b10100111 %
#1675
b11 )
b1000 *
1#
1&
#1680
0#
0&
b10101000 "
b10101000 %
b0 $
b0 '
#1685
1(
1!
b11 )
b1000 *
1#
1&
#1690
0#
0&
b10101001 "
b10101001 %
#1695
0(
0!
b11 )
b1000 *
1#
1&
b1 $
b1 '
#1700
0#
0&
b10101010 "
b10101010 %
#1705
1(
1!
b11 )
b1000 *
1#
1&
#1710
0#
0&
b10101011 "
b10101011 %
b10 $
b10 '
#1715
0(
0!
b11 )
b1000 *
1#
1&
#1720
0#
0&
b10101100 "
b10101100 %
#1725
b11 )
b1000 *
1#
1&
b11 $
b11 '
#1730
0#
0&
b10101101 "
b10101101 %
#1735
b11 )
b1000 *
1#
1&
#1740
0#
0&
b10101110 "
b10101110 %
b100 $
b100 '
#1745
b11 )
b1000 *
1#
1&
#1750
0#
0&
b10101111 "
b10101111 %
#1755
b11 )
b1000 *
1#
1&
b101 $
b101 '
#1760
0#
0&
b10110000 "
b10110000 %
#1765
b11 )
b1000 *
1#
1&
#1770
0#
0&
b10110001 "
b10110001 %
b110 $
b110 '
#1775
b11 )
b1000 *
1#
1&
#1780
0#
0&
b10110010 "
b10110010 %
#1785
b11 )
b1000 *
1#
1&
b111 $
b111 '
#1790
0#
0&
b10110011 "
b10110011 %
#1795
b11 )
b1000 *
1#
1&
#1800
0#
0&
b10110100 "
b10110100 %
b0 $
b0 '
#1805
1(
1!
b11 )
b1000 *
1#
1&
#1810
0#
0&
b10110101 "
b10110101 %
#1815
0(
0!
b11 )
b1000 *
1#
1&
b1 $
b1 '
#1820
0#
0&
b10110110 "
b10110110 %
#1825
1(
1!
b11 )
b1000 *
1#
1&
#1830
0#
0&
b10110111 "
b10110111 %
b10 $
b10 '
#1835
0(
0!
b11 )
b1000 *
1#
1&
#1840
0#
0&
b10111000 "
b10111000 %
#1845
b11 )
b1000 *
1#
1&
b11 $
b11 '
#1850
0#
0&
b10111001 "
b10111001 %
#1855
b11 )
b1000 *
1#
1&
#1860
0#
0&
b10111010 "
b10111010 %
b100 $
b100 '
#1865
b11 )
b1000 *
1#
1&
#1870
0#
0&
b10111011 "
b10111011 %
#1875
b11 )
b1000 *
1#
1&
b101 $
b101 '
#1880
0#
0&
b10111100 "
b10111100 %
#1885
b11 )
b1000 *
1#
1&
#1890
0#
0&
b10111101 "
b10111101 %
b110 $
b110 '
#1895
b11 )
b1000 *
1#
1&
#1900
0#
0&
b10111110 "
b10111110 %
#1905
b11 )
b1000 *
1#
1&
b111 $
b111 '
#1910
0#
0&
b10111111 "
b10111111 %
#1915
b11 )
b1000 *
1#
1&
#1920
0#
0&
b11000000 "
b11000000 %
b0 $
b0 '
#1925
1(
1!
b11 )
b1000 *
1#
1&
#1930
0#
0&
b11000001 "
b11000001 %
#1935
0(
0!
b11 )
b1000 *
1#
1&
b1 $
b1 '
#1940
0#
0&
b11000010 "
b11000010 %
#1945
1(
1!
b11 )
b1000 *
1#
1&
#1950
0#
0&
b11000011 "
b11000011 %
b10 $
b10 '
#1955
0(
0!
b11 )
b1000 *
1#
1&
#1960
0#
0&
b11000100 "
b11000100 %
#1965
b11 )
b1000 *
1#
1&
b11 $
b11 '
#1970
0#
0&
b11000101 "
b11000101 %
#1975
b11 )
b1000 *
1#
1&
#1980
0#
0&
b11000110 "
b11000110 %
b100 $
b100 '
#1985
b11 )
b1000 *
1#
1&
#1990
0#
0&
b11000111 "
b11000111 %
#1995
b11 )
b1000 *
1#
1&
b101 $
b101 '
#2000
0#
0&
b11001000 "
b11001000 %
#2005
b11 )
b1000 *
1#
1&
#2010
0#
0&
b11001001 "
b11001001 %
b110 $
b110 '
#2015
b11 )
b1000 *
1#
1&
#2020
0#
0&
b11001010 "
b11001010 %
#2025
b11 )
b1000 *
1#
1&
b111 $
b111 '
#2030
0#
0&
b11001011 "
b11001011 %
#2035
b11 )
b1000 *
1#
1&
#2040
0#
0&
b11001100 "
b11001100 %
b0 $
b0 '
#2045
1(
1!
b11 )
b1000 *
1#
1&
#2050
0#
0&
b11001101 "
b11001101 %
#2055
0(
0!
b11 )
b1000 *
1#
1&
b1 $
b1 '
#2060
0#
0&
b11001110 "
b11001110 %
#2065
1(
1!
b11 )
b1000 *
1#
1&
#2070
0#
0&
b11001111 "
b11001111 %
b10 $
b10 '
#2075
0(
0!
b11 )
b1000 *
1#
1&
#2080
0#
0&
b11010000 "
b11010000 %
#2085
b11 )
b1000 *
1#
1&
b11 $
b11 '
#2090
0#
0&
b11010001 "
b11010001 %
#2095
b11 )
b1000 *
1#
1&
#2100
0#
0&
b11010010 "
b11010010 %
b100 $
b100 '
#2105
b11 )
b1000 *
1#
1&
#2110
0#
0&
b11010011 "
b11010011 %
#2115
b11 )
b1000 *
1#
1&
b101 $
b101 '
#2120
0#
0&
b11010100 "
b11010100 %
#2125
b11 )
b1000 *
1#
1&
#2130
0#
0&
b11010101 "
b11010101 %
b110 $
b110 '
#2135
b11 )
b1000 *
1#
1&
#2140
0#
0&
b11010110 "
b11010110 %
#2145
b11 )
b1000 *
1#
1&
b111 $
b111 '
#2150
0#
0&
b11010111 "
b11010111 %
#2155
b11 )
b1000 *
1#
1&
#2160
0#
0&
b11011000 "
b11011000 %
b0 $
b0 '
#2165
1(
1!
b11 )
b1000 *
1#
1&
#2170
0#
0&
b11011001 "
b11011001 %
#2175
0(
0!
b11 )
b1000 *
1#
1&
b1 $
b1 '
#2180
0#
0&
b11011010 "
b11011010 %
#2185
1(
1!
b11 )
b1000 *
1#
1&
#2190
0#
0&
b11011011 "
b11011011 %
b10 $
b10 '
#2195
0(
0!
b11 )
b1000 *
1#
1&
#2200
0#
0&
b11011100 "
b11011100 %
#2205
b11 )
b1000 *
1#
1&
b11 $
b11 '
#2210
0#
0&
b11011101 "
b11011101 %
#2215
b11 )
b1000 *
1#
1&
#2220
0#
0&
b11011110 "
b11011110 %
b100 $
b100 '
#2225
b11 )
b1000 *
1#
1&
#2230
0#
0&
b11011111 "
b11011111 %
#2235
b11 )
b1000 *
1#
1&
b101 $
b101 '
#2240
0#
0&
b11100000 "
b11100000 %
#2245
b11 )
b1000 *
1#
1&
#2250
0#
0&
b11100001 "
b11100001 %
b110 $
b110 '
#2255
b11 )
b1000 *
1#
1&
#2260
0#
0&
b11100010 "
b11100010 %
#2265
b11 )
b1000 *
1#
1&
b111 $
b111 '
#2270
0#
0&
b11100011 "
b11100011 %
#2275
b11 )
b1000 *
1#
1&
#2280
0#
0&
b11100100 "
b11100100 %
b0 $
b0 '
#2285
1(
1!
b11 )
b1000 *
1#
1&
#2290
0#
0&
b11100101 "
b11100101 %
#2295
0(
0!
b11 )
b1000 *
1#
1&
b1 $
b1 '
#2300
0#
0&
b11100110 "
b11100110 %
#2305
1(
1!
b11 )
b1000 *
1#
1&
#2310
0#
0&
b11100111 "
b11100111 %
b10 $
b10 '
#2315
0(
0!
b11 )
b1000 *
1#
1&
#2320
0#
0&
b11101000 "
b11101000 %
#2325
b11 )
b1000 *
1#
1&
b11 $
b11 '
#2330
0#
0&
b11101001 "
b11101001 %
#2335
b11 )
b1000 *
1#
1&
#2340
0#
0&
b11101010 "
b11101010 %
b100 $
b100 '
#2345
b11 )
b1000 *
1#
1&
#2350
0#
0&
b11101011 "
b11101011 %
#2355
b11 )
b1000 *
1#
1&
b101 $
b101 '
#2360
0#
0&
b11101100 "
b11101100 %
#2365
b11 )
b1000 *
1#
1&
#2370
0#
0&
b11101101 "
b11101101 %
b110 $
b110 '
#2375
b11 )
b1000 *
1#
1&
#2380
0#
0&
b11101110 "
b11101110 %
#2385
b11 )
b1000 *
1#
1&
b111 $
b111 '
#2390
0#
0&
b11101111 "
b11101111 %
#2395
b11 )
b1000 *
1#
1&
#2400
0#
0&
b11110000 "
b11110000 %
b0 $
b0 '
#2405
1(
1!
b11 )
b1000 *
1#
1&
#2410
0#
0&
b11110001 "
b11110001 %
#2415
0(
0!
b11 )
b1000 *
1#
1&
b1 $
b1 '
#2420
0#
0&
b11110010 "
b11110010 %
#2425
1(
1!
b11 )
b1000 *
1#
1&
#2430
0#
0&
b11110011 "
b11110011 %
b10 $
b10 '
#2435
0(
0!
b11 )
b1000 *
1#
1&
#2440
0#
0&
b11110100 "
b11110100 %
#2445
b11 )
b1000 *
1#
1&
b11 $
b11 '
#2450
0#
0&
b11110101 "
b11110101 %
#2455
b11 )
b1000 *
1#
1&
#2460
0#
0&
b11110110 "
b11110110 %
b100 $
b100 '
#2465
b11 )
b1000 *
1#
1&
#2470
0#
0&
b11110111 "
b11110111 %
#2475
b11 )
b1000 *
1#
1&
b101 $
b101 '
#2480
0#
0&
b11111000 "
b11111000 %
#2485
b11 )
b1000 *
1#
1&
#2490
0#
0&
b11111001 "
b11111001 %
b110 $
b110 '
#2495
b11 )
b1000 *
1#
1&
#2500
0#
0&
b11111010 "
b11111010 %
#2505
b11 )
b1000 *
1#
1&
b111 $
b111 '
#2510
0#
0&
b11111011 "
b11111011 %
#2515
b11 )
b1000 *
1#
1&
#2520
0#
0&
b11111100 "
b11111100 %
b0 $
b0 '
#2525
1(
1!
b11 )
b1000 *
1#
1&
#2530
0#
0&
b11111101 "
b11111101 %
#2535
0(
0!
b11 )
b1000 *
1#
1&
b1 $
b1 '
#2540
0#
0&
b11111110 "
b11111110 %
#2545
1(
1!
b11 )
b1000 *
1#
1&
#2550
0#
0&
b11111111 "
b11111111 %
b10 $
b10 '
#2555
0(
0!
b11 )
b1000 *
1#
1&
#2560
0#
0&
b0 "
b0 %
#2565
b11 )
b1000 *
1#
1&
b11 $
b11 '
#2570
0#
0&
b1 "
b1 %
#2575
b11 )
b1000 *
1#
1&
#2580
0#
0&
b10 "
b10 %
b100 $
b100 '
#2585
b11 )
b1000 *
1#
1&
#2590
0#
0&
b11 "
b11 %
#2595
b11 )
b1000 *
1#
1&
b101 $
b101 '
#2600
0#
0&
b100 "
b100 %
#2605
b11 )
b1000 *
1#
1&
#2610
0#
0&
b101 "
b101 %
b110 $
b110 '
#2615
b11 )
b1000 *
1#
1&
#2620
0#
0&
b110 "
b110 %
#2625
b11 )
b1000 *
1#
1&
b111 $
b111 '
#2630
0#
0&
b111 "
b111 %
#2635
b11 )
b1000 *
1#
1&
#2640
0#
0&
b1000 "
b1000 %
b0 $
b0 '
#2645
1(
1!
b11 )
b1000 *
1#
1&
#2650
0#
0&
b1001 "
b1001 %
#2655
0(
0!
b11 )
b1000 *
1#
1&
b1 $
b1 '
#2660
0#
0&
b1010 "
b1010 %
#2665
1(
1!
b11 )
b1000 *
1#
1&
#2670
0#
0&
b1011 "
b1011 %
b10 $
b10 '
#2675
0(
0!
b11 )
b1000 *
1#
1&
#2680
0#
0&
b1100 "
b1100 %
#2685
b11 )
b1000 *
1#
1&
b11 $
b11 '
#2690
0#
0&
b1101 "
b1101 %
#2695
b11 )
b1000 *
1#
1&
#2700
0#
0&
b1110 "
b1110 %
b100 $
b100 '
#2705
b11 )
b1000 *
1#
1&
#2710
0#
0&
b1111 "
b1111 %
#2715
b11 )
b1000 *
1#
1&
b101 $
b101 '
#2720
0#
0&
b10000 "
b10000 %
#2725
b11 )
b1000 *
1#
1&
#2730
0#
0&
b10001 "
b10001 %
b110 $
b110 '
#2735
b11 )
b1000 *
1#
1&
#2740
0#
0&
b10010 "
b10010 %
