mux21.v
module mux21 (y, sel, i0, i1);
    input sel, i0, i1;
    output y;
    //not g0(selb, sel);
    and g1(w1, i0, ~sel);
    and g2(w2, i1, sel);
    or g3(y, w1, w2);
    
endmodule

mux21_tb.v
`include "mux21.v"
module mux21_tb;
    reg sel, i0, i1;
    wire y;
    mux21 mux21_tb_i (
        .y(y), 
        .sel(sel),
        .i0(i0),
        .i1(i1)
        );
        initial begin
            $dumpfile("mux21.vcd");
            $dumpvars (0, mux21_tb);
            sel=0; i1=0; i0=0;
        #10 sel=0; i1=0; i0=1;
        #10 sel=0; i1=1; i0=0;
        #10 sel=0; i1=1; i0=1;
        #10 sel=1; i1=0; i0=0;
        #10 sel=1; i1=0; i0=1;
        #10 sel=1; i1=1; i0=0;
        #10 sel=1; i1=1; i0=1;

        #10 sel=0; i1=0; i0=0;
        #10 sel=0; i1=0; i0=1;
        #10 sel=0; i1=1; i0=0;
        #10 sel=0; i1=1; i0=1;
        #10 sel=1; i1=0; i0=0;
        #10 sel=1; i1=0; i0=1;
        #10 sel=1; i1=1; i0=0;
        #10 sel=1; i1=1; i0=1;

        #250 $finish;

        end
endmodule

mux21.vcd
$date
	Fri Apr 14 19:48:43 2023
$end
$version
	Icarus Verilog
$end
$timescale
	1s
$end
$scope module mux21_tb $end
$var wire 1 ! y $end
$var reg 1 " i0 $end
$var reg 1 # i1 $end
$var reg 1 $ sel $end
$scope module mux21_tb_i $end
$var wire 1 % i0 $end
$var wire 1 & i1 $end
$var wire 1 ' sel $end
$var wire 1 ( w1 $end
$var wire 1 ) w2 $end
$var wire 1 ! y $end
$upscope $end
$upscope $end
$enddefinitions $end
#0
$dumpvars
0)
0(
0'
0&
0%
0$
0#
0"
0!
$end
#10
1!
1(
1"
1%
#20
0!
0(
0"
0%
1#
1&
#30
1!
1(
1"
1%
#40
0!
0(
0"
0%
0#
0&
1$
1'
#50
1"
1%
#60
1!
1)
0"
0%
1#
1&
#70
1"
1%
#80
0!
0)
0"
0%
0#
0&
0$
0'
#90
1!
1(
1"
1%
#100
0!
0(
0"
0%
1#
1&
#110
1!
1(
1"
1%
#120
0!
0(
0"
0%
0#
0&
1$
1'
#130
1"
1%
#140
1!
1)
0"
0%
1#
1&
#150
1"
1%
